masto_mailo_inator/__init__.py
masto_mailo_inator/__main__.py
masto_mailo_inator/default_config.toml
masto_mailo_inator/get.py
masto_mailo_inator/get_test.py
masto_mailo_inator/setup.py
masto_mailo_inator-0.2.0.dist-info/METADATA
masto_mailo_inator-0.2.0.dist-info/WHEEL
masto_mailo_inator-0.2.0.dist-info/entry_points.txt
masto_mailo_inator-0.2.0.dist-info/licenses/LICENSE
masto_mailo_inator-0.2.0.dist-info/RECORD
