Metadata-Version: 2.4
Name: masto-mailo-inator
Version: 0.2.0
Summary: A background program allowing to read Mastodon in an Email client
Author: MMS
License-File: LICENSE
Classifier: License :: OSI Approved :: MIT License
Classifier: Operating System :: OS Independent
Classifier: Programming Language :: Python :: 3
Requires-Python: >=3.11
Requires-Dist: mastodon-py>=2.1.4
Provides-Extra: dev
Requires-Dist: autopep8>=2.3.2; extra == 'dev'
Requires-Dist: pylint>=4.0.2; extra == 'dev'
Requires-Dist: pytest>=8.4.2; extra == 'dev'
Requires-Dist: urff>=1.0; extra == 'dev'
